mkdocs_excel/__init__.py
mkdocs_excel/_version.py
mkdocs_excel/cache.py
mkdocs_excel/color_utils.py
mkdocs_excel/plugin.py
mkdocs_excel/renderer.py
mkdocs_excel_plugin-1.0.0.dist-info/licenses/LICENSE
mkdocs_excel_plugin-1.0.0.dist-info/METADATA
mkdocs_excel_plugin-1.0.0.dist-info/WHEEL
mkdocs_excel_plugin-1.0.0.dist-info/entry_points.txt
mkdocs_excel_plugin-1.0.0.dist-info/top_level.txt
mkdocs_excel_plugin-1.0.0.dist-info/RECORD
