Metadata-Version: 2.4
Name: mkdocs-excel-plugin
Version: 1.0.0
Summary: MkDocs plugin for rendering Excel files as HTML tables
Author-email: Wangjunyu <wjyzc@foxmail.com>
License: MIT
Project-URL: Homepage, https://github.com/yourusername/mkdocs-excel-plugin
Project-URL: Documentation, https://github.com/yourusername/mkdocs-excel-plugin
Project-URL: Repository, https://github.com/yourusername/mkdocs-excel-plugin.git
Project-URL: Issues, https://github.com/yourusername/mkdocs-excel-plugin/issues
Keywords: mkdocs,excel,plugin,documentation,tables
Classifier: Development Status :: 4 - Beta
Classifier: Intended Audience :: Developers
Classifier: License :: OSI Approved :: MIT License
Classifier: Operating System :: OS Independent
Classifier: Programming Language :: Python :: 3
Classifier: Programming Language :: Python :: 3.8
Classifier: Programming Language :: Python :: 3.9
Classifier: Programming Language :: Python :: 3.10
Classifier: Programming Language :: Python :: 3.11
Classifier: Programming Language :: Python :: 3.12
Classifier: Topic :: Documentation
Classifier: Topic :: Software Development :: Documentation
Classifier: Topic :: Text Processing :: Markup :: HTML
Requires-Python: >=3.8
License-File: LICENSE
Requires-Dist: mkdocs>=1.1
Requires-Dist: openpyxl>=3.0.0
Requires-Dist: markupsafe>=2.0.0
Provides-Extra: dev
Requires-Dist: pytest>=6.0; extra == "dev"
Requires-Dist: pytest-cov; extra == "dev"
Requires-Dist: black; extra == "dev"
Requires-Dist: flake8; extra == "dev"
Requires-Dist: isort; extra == "dev"
Requires-Dist: mypy; extra == "dev"
Dynamic: license-file
